{"id":"02-ml-fundamentals/06-knn-and-distances","phase":"02-ml-fundamentals","slug":"06-knn-and-distances","title":"K-Nearest Neighbors and Distances","titleZh":"K 近邻与距离度量","quote":"Store everything. Predict by looking at your neighbors. The simplest algorithm that actually works.","meta":{"type":"Build","prerequisites":"Phase 1 (Lesson 14 Norms and Distances)","time":"~90 minutes"},"bodyEn":"# K-Nearest Neighbors and Distances\n\n> Store everything. Predict by looking at your neighbors. The simplest algorithm that actually works.\n\n**Type:** Build\n**Language:** Python\n**Prerequisites:** Phase 1 (Lesson 14 Norms and Distances)\n**Time:** ~90 minutes\n\n## Learning Objectives\n\n- Implement KNN classification and regression from scratch with configurable K and distance-weighted voting\n- Compare L1, L2, cosine, and Minkowski distance metrics and select the appropriate one for a given data type\n- Explain the curse of dimensionality and demonstrate why KNN degrades in high-dimensional spaces\n- Build a KD-tree for efficient nearest neighbor search and analyze when it outperforms brute-force\n\n## The Problem\n\nYou have a dataset. A new data point arrives. You need to classify it or predict its value. Instead of learning parameters from the data (like linear regression or SVMs), you just find the K training points closest to the new point and let them vote.\n\nThis is K-nearest neighbors. There is no training phase. No parameters to learn. No loss function to minimize. You store the entire training set and compute distances at prediction time.\n\nIt sounds too simple to work. But KNN is surprisingly competitive for many problems, especially with small to medium datasets, and understanding it deeply reveals fundamental concepts: the choice of distance metric (connecting to Phase 1 Lesson 14), the curse of dimensionality, and the difference between lazy and eager learning.\n\nKNN also shows up everywhere in modern AI, just under different names. Vector databases do KNN search over embeddings. Retrieval-augmented generation (RAG) finds the K nearest document chunks. Recommendation systems find similar users or items. The algorithm is the same. The scale and the data structures are different.\n\n## The Concept\n\n### How KNN works\n\nGiven a dataset of labeled points and a new query point:\n\n1. Compute the distance from the query to every point in the dataset\n2. Sort by distance\n3. Take the K closest points\n4. For classification: majority vote among the K neighbors\n5. For regression: average (or weighted average) of the K neighbors' values\n\n```mermaid\ngraph TD\n    Q[\"Query point ?\"] --> D[\"Compute distances<br>to all training points\"]\n    D --> S[\"Sort by distance\"]\n    S --> K[\"Select K nearest\"]\n    K --> C{\"Classification<br>or Regression?\"}\n    C -->|Classification| V[\"Majority vote\"]\n    C -->|Regression| A[\"Average values\"]\n    V --> P[\"Prediction\"]\n    A --> P\n```\n\nThat is the entire algorithm. No fitting. No gradient descent. No epochs.\n\n### Choosing K\n\nK is the single hyperparameter. It controls the bias-variance trade-off:\n\n| K | Behavior |\n|---|----------|\n| K = 1 | Decision boundary follows every point. Zero training error. High variance. Overfits |\n| Small K (3-5) | Sensitive to local structure. Can capture complex boundaries |\n| Large K | Smoother boundaries. More robust to noise. May underfit |\n| K = N | Predicts the majority class for every point. Maximum bias |\n\nA common starting point is K = sqrt(N) for a dataset of N points. Use odd K for binary classification to avoid ties.\n\n```mermaid\ngraph LR\n    subgraph \"K=1 (overfitting)\"\n        A[\"Jagged boundary<br>follows every point\"]\n    end\n    subgraph \"K=15 (good)\"\n        B[\"Smooth boundary<br>captures true pattern\"]\n    end\n    subgraph \"K=N (underfitting)\"\n        C[\"Flat boundary<br>predicts majority class\"]\n    end\n    A -->|\"increase K\"| B -->|\"increase K\"| C\n```\n\n### Distance metrics\n\nThe distance function defines what \"near\" means. Different metrics produce different neighbors, different predictions.\n\n**L2 (Euclidean)** is the default. Straight-line distance.\n\n```\nd(a, b) = sqrt(sum((a_i - b_i)^2))\n```\n\nSensitive to feature scale. Always standardize features before using L2 with KNN.\n\n**L1 (Manhattan)** sums absolute differences. More robust to outliers than L2 because it does not square the differences.\n\n```\nd(a, b) = sum(|a_i - b_i|)\n```\n\n**Cosine distance** measures the angle between vectors, ignoring magnitude. Essential for text and embedding data.\n\n```\nd(a, b) = 1 - (a . b) / (||a|| * ||b||)\n```\n\n**Minkowski** generalizes L1 and L2 with parameter p.\n\n```\nd(a, b) = (sum(|a_i - b_i|^p))^(1/p)\n\np=1: Manhattan\np=2: Euclidean\np->inf: Chebyshev (max absolute difference)\n```\n\nWhich metric to use depends on the data:\n\n| Data type | Best metric | Why |\n|-----------|------------|-----|\n| Numeric features, similar scale | L2 (Euclidean) | Default, works for spatial data |\n| Numeric features, outliers | L1 (Manhattan) | Robust, does not amplify large differences |\n| Text embeddings | Cosine | Magnitude is noise, direction is meaning |\n| High-dimensional sparse | Cosine or L1 | L2 suffers from curse of dimensionality |\n| Mixed types | Custom distance | Combine metrics per feature type |\n\n### Weighted KNN\n\nStandard KNN gives equal weight to all K neighbors. But a neighbor at distance 0.1 should matter more than one at distance 5.0.\n\n**Distance-weighted KNN** weights each neighbor inversely by distance:\n\n```\nweight_i = 1 / (distance_i + epsilon)\n\nFor classification: weighted vote\nFor regression:     weighted average = sum(w_i * y_i) / sum(w_i)\n```\n\nThe epsilon prevents division by zero when a query point exactly matches a training point.\n\nWeighted KNN is less sensitive to the choice of K because distant neighbors contribute very little regardless.\n\n### The curse of dimensionality\n\nKNN performance degrades in high dimensions. This is not a vague concern. It is a mathematical fact.\n\n**Problem 1: distances converge.** As dimensionality increases, the ratio of the maximum distance to the minimum distance approaches 1. All points become equally \"far\" from the query.\n\n```\nIn d dimensions, for random uniform points:\n\nd=2:    max_dist / min_dist = varies widely\nd=100:  max_dist / min_dist ~ 1.01\nd=1000: max_dist / min_dist ~ 1.001\n\nWhen all distances are nearly equal, \"nearest\" is meaningless.\n```\n\n**Problem 2: volume explodes.** To capture K neighbors within a fixed fraction of the data, you need to extend your search radius to cover a much larger fraction of the feature space. The \"neighborhood\" in high dimensions encompasses most of the space.\n\n**Problem 3: corners dominate.** In a unit hypercube in d dimensions, most of the volume is concentrated near the corners, not the center. A sphere inscribed in the cube contains a vanishing fraction of the volume as d grows.\n\nPractical consequence: KNN works well up to about 20-50 features. Beyond that, you need dimensionality reduction (PCA, UMAP, t-SNE) before applying KNN, or you need to use tree-based search structures that exploit the data's intrinsic lower dimensionality.\n\n### KD-trees: fast nearest neighbor search\n\nBrute-force KNN computes the distance from the query to every training point. That is O(n * d) per query. For large datasets, this is too slow.\n\nA KD-tree recursively partitions the space along feature axes. At each level, it splits along one dimension at the median value.\n\n```mermaid\ngraph TD\n    R[\"Split on x1 at 5.0\"] -->|\"x1 <= 5.0\"| L[\"Split on x2 at 3.0\"]\n    R -->|\"x1 > 5.0\"| RR[\"Split on x2 at 7.0\"]\n    L -->|\"x2 <= 3.0\"| LL[\"Leaf: 3 points\"]\n    L -->|\"x2 > 3.0\"| LR[\"Leaf: 4 points\"]\n    RR -->|\"x2 <= 7.0\"| RL[\"Leaf: 2 points\"]\n    RR -->|\"x2 > 7.0\"| RRR[\"Leaf: 5 points\"]\n```\n\nTo find the nearest neighbor, traverse the tree to the leaf containing the query, then backtrack and check neighboring partitions only if they could contain closer points.\n\nAverage query time: O(log n) for low dimensions. But KD-trees degrade to O(n) in high dimensions (d > 20) because the backtracking eliminates fewer and fewer branches.\n\n### Ball trees: better for moderate dimensions\n\nBall trees partition data into nested hyperspheres instead of axis-aligned boxes. Each node defines a ball (center + radius) that contains all points in that subtree.\n\nAdvantages over KD-trees:\n- Work better in moderate dimensions (up to ~50)\n- Handle non-axis-aligned structure\n- Tighter bounding volumes mean more branches are pruned during search\n\nBoth KD-trees and ball trees are exact algorithms. For truly large-scale search (millions of points, hundreds of dimensions), approximate nearest neighbor methods (HNSW, IVF, product quantization) are used instead. These are covered in Phase 1 Lesson 14.\n\n### Lazy learning vs eager learning\n\nKNN is a lazy learner: it does no work at training time and all work at prediction time. Most other algorithms (linear regression, SVMs, neural networks) are eager learners: they do heavy computation at training time to build a compact model, then predictions are fast.\n\n| Aspect | Lazy (KNN) | Eager (SVM, neural net) |\n|--------|------------|------------------------|\n| Training time | O(1) just store data | O(n * epochs) |\n| Prediction time | O(n * d) per query | O(d) or O(parameters) |\n| Memory at prediction | Store entire training set | Store model parameters only |\n| Adapts to new data | Add points instantly | Retrain the model |\n| Decision boundary | Implicit, computed on the fly | Explicit, fixed after training |\n\nLazy learning is ideal when:\n- The dataset changes frequently (add/remove points without retraining)\n- You need predictions for very few queries\n- You want zero training time\n- The dataset is small enough that brute-force search is fast\n\n### KNN for regression\n\nInstead of majority voting, KNN for regression averages the target values of the K neighbors.\n\n```\nprediction = (1/K) * sum(y_i for i in K nearest neighbors)\n\nOr with distance weighting:\nprediction = sum(w_i * y_i) / sum(w_i)\nwhere w_i = 1 / distance_i\n```\n\nKNN regression produces piecewise-constant (or piecewise-smooth with weighting) predictions. It cannot extrapolate beyond the range of the training data. If the training targets are all between 0 and 100, KNN will never predict 200.\n\n```figure\nknn-smoothness\n```\n\n## Build It\n\n### Step 1: Distance functions\n\nImplement L1, L2, cosine, and Minkowski distances. These connect directly to Phase 1 Lesson 14.\n\n```python\nimport math\n\ndef l2_distance(a, b):\n    return math.sqrt(sum((ai - bi) ** 2 for ai, bi in zip(a, b)))\n\ndef l1_distance(a, b):\n    return sum(abs(ai - bi) for ai, bi in zip(a, b))\n\ndef cosine_distance(a, b):\n    dot_val = sum(ai * bi for ai, bi in zip(a, b))\n    norm_a = math.sqrt(sum(ai ** 2 for ai in a))\n    norm_b = math.sqrt(sum(bi ** 2 for bi in b))\n    if norm_a == 0 or norm_b == 0:\n        return 1.0\n    return 1.0 - dot_val / (norm_a * norm_b)\n\ndef minkowski_distance(a, b, p=2):\n    if p == float('inf'):\n        return max(abs(ai - bi) for ai, bi in zip(a, b))\n    return sum(abs(ai - bi) ** p for ai, bi in zip(a, b)) ** (1 / p)\n```\n\n### Step 2: KNN classifier and regressor\n\nBuild the full KNN with configurable K, distance metric, and optional distance weighting.\n\n```python\nclass KNN:\n    def __init__(self, k=5, distance_fn=l2_distance, weighted=False,\n                 task=\"classification\"):\n        self.k = k\n        self.distance_fn = distance_fn\n        self.weighted = weighted\n        self.task = task\n        self.X_train = None\n        self.y_train = None\n\n    def fit(self, X, y):\n        self.X_train = X\n        self.y_train = y\n\n    def predict(self, X):\n        return [self._predict_one(x) for x in X]\n```\n\n### Step 3: KD-tree for efficient search\n\nBuild a KD-tree from scratch that recursively splits on the median of each dimension.\n\n```python\nclass KDTree:\n    def __init__(self, X, indices=None, depth=0):\n        # Recursively partition the data\n        self.axis = depth % len(X[0])\n        # Split on median of the current axis\n        ...\n\n    def query(self, point, k=1):\n        # Traverse to leaf, then backtrack\n        ...\n```\n\nSee `code/knn.py` for the complete implementation with all helper methods and demos.\n\n### Step 4: Feature scaling\n\nKNN requires feature scaling because distances are sensitive to feature magnitudes. A feature ranging from 0 to 1000 will dominate a feature ranging from 0 to 1.\n\n```python\ndef standardize(X):\n    n = len(X)\n    d = len(X[0])\n    means = [sum(X[i][j] for i in range(n)) / n for j in range(d)]\n    stds = [\n        max(1e-10, (sum((X[i][j] - means[j]) ** 2 for i in range(n)) / n) ** 0.5)\n        for j in range(d)\n    ]\n    return [[((X[i][j] - means[j]) / stds[j]) for j in range(d)] for i in range(n)], means, stds\n```\n\n## Use It\n\nWith scikit-learn:\n\n```python\nfrom sklearn.neighbors import KNeighborsClassifier\nfrom sklearn.preprocessing import StandardScaler\nfrom sklearn.pipeline import Pipeline\n\nclf = Pipeline([\n    (\"scaler\", StandardScaler()),\n    (\"knn\", KNeighborsClassifier(n_neighbors=5, metric=\"euclidean\")),\n])\nclf.fit(X_train, y_train)\nprint(f\"Accuracy: {clf.score(X_test, y_test):.4f}\")\n```\n\nScikit-learn automatically uses KD-trees or ball trees when the dataset is large enough and the dimensionality is low enough. For high-dimensional data, it falls back to brute force. You can control this with the `algorithm` parameter.\n\nFor large-scale nearest neighbor search (millions of vectors), use FAISS, Annoy, or a vector database:\n\n```python\nimport faiss\n\nindex = faiss.IndexFlatL2(dimension)\nindex.add(embeddings)\ndistances, indices = index.search(query_vectors, k=5)\n```\n\n## Exercises\n\n1. Implement KNN classification on a 2D dataset with 3 classes. Plot the decision boundary for K=1, K=5, K=15, and K=N. Observe the transition from overfitting to underfitting.\n\n2. Generate 1000 random points in 2, 5, 10, 50, 100, and 500 dimensions. For each dimensionality, compute the ratio of the maximum pairwise distance to the minimum pairwise distance. Plot the ratio vs dimensionality to visualize the curse of dimensionality.\n\n3. Compare L1, L2, and cosine distance for KNN on a text classification problem (use TF-IDF vectors). Which metric gives the best accuracy? Why does cosine tend to win for text?\n\n4. Implement a KD-tree and measure query time vs brute force for datasets of 1k, 10k, and 100k points in 2D, 10D, and 50D. At what dimensionality does the KD-tree stop being faster than brute force?\n\n5. Build a weighted KNN regressor for y = sin(x) + noise. Compare it with unweighted KNN for K=3, 10, 30. Show that weighting produces smoother predictions, especially for large K.\n\n## Key Terms\n\n| Term | What it actually means |\n|------|----------------------|\n| K-nearest neighbors | Non-parametric algorithm that predicts by finding the K closest training points to a query |\n| Lazy learning | No computation at training time. All work happens at prediction time. KNN is the canonical example |\n| Eager learning | Heavy computation at training time to build a compact model. Most ML algorithms are eager |\n| Curse of dimensionality | In high dimensions, distances converge and neighborhoods expand to cover most of the space, making KNN ineffective |\n| KD-tree | Binary tree that recursively partitions space along feature axes. O(log n) queries in low dimensions |\n| Ball tree | Tree of nested hyperspheres. Works better than KD-trees in moderate dimensions (up to ~50) |\n| Weighted KNN | Neighbors weighted inversely by distance. Closer neighbors have more influence on the prediction |\n| Feature scaling | Normalizing features to comparable ranges. Required for distance-based methods like KNN |\n| Majority vote | Classification by counting which class is most common among K neighbors |\n| Brute force search | Computing distance to every training point. O(n*d) per query. Exact but slow for large n |\n| Approximate nearest neighbor | Algorithms (HNSW, LSH, IVF) that find approximately nearest points much faster than exact search |\n| Voronoi diagram | The partition of space where each region contains all points closer to one training point than any other. K=1 KNN produces Voronoi boundaries |\n\n## Further Reading\n\n- [Cover & Hart: Nearest Neighbor Pattern Classification (1967)](https://ieeexplore.ieee.org/document/1053964) - the foundational KNN paper proving it has error rate at most twice the Bayes optimal\n- [Friedman, Bentley, Finkel: An Algorithm for Finding Best Matches in Logarithmic Expected Time (1977)](https://dl.acm.org/doi/10.1145/355744.355745) - the original KD-tree paper\n- [Beyer et al.: When Is \"Nearest Neighbor\" Meaningful? (1999)](https://link.springer.com/chapter/10.1007/3-540-49257-7_15) - formal analysis of the curse of dimensionality for nearest neighbor\n- [scikit-learn Nearest Neighbors documentation](https://scikit-learn.org/stable/modules/neighbors.html) - practical guide with algorithm selection\n- [FAISS: A Library for Efficient Similarity Search](https://github.com/facebookresearch/faiss) - Meta's library for billion-scale approximate nearest neighbor search\n","bodyZh":"# K 近邻与距离\n\n> 存下所有数据，预测时看邻居。最简单却真正管用的算法。\n\n**Type:** Build\n**Language:** Python\n**Prerequisites:** Phase 1 (Lesson 14 Norms and Distances)\n**Time:** ~90 minutes\n\n## 学习目标\n\n- 从零实现 KNN 分类与回归，支持可配置的 K 值和距离加权投票\n- 比较 L1、L2、余弦和 Minkowski 距离度量，并能针对给定数据类型选择合适的度量\n- 解释维度灾难（curse of dimensionality），并演示 KNN 为何在高维空间中性能退化\n- 构建 KD 树以实现高效的最近邻搜索，并分析它在何时优于暴力搜索\n\n## 问题背景\n\n你有一个数据集，一个新数据点到来，你需要对它进行分类或预测它的值。与从数据中学习参数的方法（如线性回归或 SVM）不同，你只需找到离新数据点最近的 K 个训练点，让它们投票决定结果。\n\n这就是 K 近邻（K-nearest neighbors）。它没有训练阶段，没有要学习的参数，没有要最小化的损失函数。你存储整个训练集，在预测时才计算距离。\n\n听起来简单到不像能管用。但在许多问题上 KNN 的竞争力出人意料，尤其是中小规模数据集；而且深入理解它能揭示一些基础概念：距离度量的选择（呼应 Phase 1 第 14 课）、维度灾难，以及惰性学习与积极学习的区别。\n\nKNN 也以不同的名字出现在现代 AI 的各个角落。向量数据库在嵌入（embedding）上做 KNN 搜索；检索增强生成（RAG）查找最近的 K 个文档块；推荐系统寻找相似的用户或物品。算法是同一个，不同的只是规模和数据结构。\n\n## 核心概念\n\n### KNN 的工作原理\n\n给定一个带标签的数据集和一个新的查询点：\n\n1. 计算查询点到数据集中每个点的距离\n2. 按距离排序\n3. 取最近的 K 个点\n4. 分类任务：在 K 个邻居中进行多数投票\n5. 回归任务：对 K 个邻居的值取平均（或加权平均）\n\n```mermaid\ngraph TD\n    Q[\"Query point ?\"] --> D[\"Compute distances<br>to all training points\"]\n    D --> S[\"Sort by distance\"]\n    S --> K[\"Select K nearest\"]\n    K --> C{\"Classification<br>or Regression?\"}\n    C -->|Classification| V[\"Majority vote\"]\n    C -->|Regression| A[\"Average values\"]\n    V --> P[\"Prediction\"]\n    A --> P\n```\n\n这就是整个算法。没有拟合，没有梯度下降，没有训练轮次。\n\n### 选择 K\n\nK 是唯一的超参数。它控制偏差-方差权衡：\n\n| K | 行为 |\n|---|----------|\n| K = 1 | 决策边界跟随每一个点。训练误差为零。方差高。过拟合 |\n| 较小的 K（3-5） | 对局部结构敏感。能捕捉复杂的边界 |\n| 较大的 K | 边界更平滑。对噪声更稳健。可能欠拟合 |\n| K = N | 对每个点都预测多数类。偏差最大 |\n\n对于包含 N 个点的数据集，一个常见的起点是 K = sqrt(N)。二分类时使用奇数 K 以避免平票。\n\n```mermaid\ngraph LR\n    subgraph \"K=1 (overfitting)\"\n        A[\"Jagged boundary<br>follows every point\"]\n    end\n    subgraph \"K=15 (good)\"\n        B[\"Smooth boundary<br>captures true pattern\"]\n    end\n    subgraph \"K=N (underfitting)\"\n        C[\"Flat boundary<br>predicts majority class\"]\n    end\n    A -->|\"increase K\"| B -->|\"increase K\"| C\n```\n\n### 距离度量\n\n距离函数定义了\"近\"的含义。不同的度量会产生不同的邻居、不同的预测。\n\n**L2（欧氏距离）**是默认选择。即直线距离。\n\n```\nd(a, b) = sqrt(sum((a_i - b_i)^2))\n```\n\n对特征尺度敏感。在 KNN 中使用 L2 之前务必先对特征做标准化。\n\n**L1（曼哈顿距离）**对绝对差值求和。由于不对差值取平方，它比 L2 对离群值更稳健。\n\n```\nd(a, b) = sum(|a_i - b_i|)\n```\n\n**余弦距离**衡量向量之间的夹角，忽略模长。对文本和嵌入数据至关重要。\n\n```\nd(a, b) = 1 - (a . b) / (||a|| * ||b||)\n```\n\n**Minkowski 距离**通过参数 p 推广了 L1 和 L2。\n\n```\nd(a, b) = (sum(|a_i - b_i|^p))^(1/p)\n\np=1: Manhattan\np=2: Euclidean\np->inf: Chebyshev (max absolute difference)\n```\n\n选用哪种度量取决于数据：\n\n| 数据类型 | 最佳度量 | 原因 |\n|-----------|------------|-----|\n| 数值特征，尺度相近 | L2（欧氏） | 默认选择，适合空间数据 |\n| 数值特征，存在离群值 | L1（曼哈顿） | 稳健，不会放大较大的差值 |\n| 文本嵌入 | 余弦 | 模长是噪声，方向才是语义 |\n| 高维稀疏数据 | 余弦或 L1 | L2 受维度灾难影响 |\n| 混合类型 | 自定义距离 | 按特征类型组合不同度量 |\n\n### 加权 KNN\n\n标准 KNN 对所有 K 个邻居一视同仁。但距离 0.1 的邻居理应比距离 5.0 的邻居更重要。\n\n**距离加权 KNN** 按距离的倒数为每个邻居赋权：\n\n```\nweight_i = 1 / (distance_i + epsilon)\n\nFor classification: weighted vote\nFor regression:     weighted average = sum(w_i * y_i) / sum(w_i)\n```\n\nepsilon 用来防止查询点与某个训练点完全重合时出现除零。\n\n加权 KNN 对 K 的选择不那么敏感，因为无论如何，遥远的邻居贡献都很小。\n\n### 维度灾难\n\nKNN 的性能在高维下会退化。这不是一种模糊的担忧，而是数学事实。\n\n**问题 1：距离趋同。**随着维度增加，最大距离与最小距离之比趋近于 1。所有点到查询点的距离变得几乎一样\"远\"。\n\n```\nIn d dimensions, for random uniform points:\n\nd=2:    max_dist / min_dist = varies widely\nd=100:  max_dist / min_dist ~ 1.01\nd=1000: max_dist / min_dist ~ 1.001\n\nWhen all distances are nearly equal, \"nearest\" is meaningless.\n```\n\n**问题 2：体积爆炸。**要在数据的固定比例内捕获 K 个邻居，你需要把搜索半径扩展到覆盖特征空间中大得多的比例。高维中的\"邻域\"几乎囊括了整个空间。\n\n**问题 3：角落主导。**在 d 维单位超立方体中，大部分体积集中在角落附近，而不是中心。随着 d 增大，内切于立方体的球体所占的体积比例趋于零。\n\n实际影响：KNN 在大约 20-50 个特征以内表现良好。超过这个范围，你需要在应用 KNN 之前先做降维（PCA、UMAP、t-SNE），或者使用能利用数据内在低维结构的树形搜索结构。\n\n### KD 树：快速最近邻搜索\n\n暴力 KNN 要计算查询点到每个训练点的距离，每次查询的开销是 O(n * d)。对大数据集来说太慢了。\n\nKD 树（KD-tree）沿特征轴递归地划分空间。在每一层，它在某一维度的中位数处进行切分。\n\n```mermaid\ngraph TD\n    R[\"Split on x1 at 5.0\"] -->|\"x1 <= 5.0\"| L[\"Split on x2 at 3.0\"]\n    R -->|\"x1 > 5.0\"| RR[\"Split on x2 at 7.0\"]\n    L -->|\"x2 <= 3.0\"| LL[\"Leaf: 3 points\"]\n    L -->|\"x2 > 3.0\"| LR[\"Leaf: 4 points\"]\n    RR -->|\"x2 <= 7.0\"| RL[\"Leaf: 2 points\"]\n    RR -->|\"x2 > 7.0\"| RRR[\"Leaf: 5 points\"]\n```\n\n要查找最近邻，先沿树遍历到包含查询点的叶子节点，然后回溯，仅在相邻分区可能包含更近的点时才去检查它们。\n\n平均查询时间：低维下为 O(log n)。但在高维（d > 20）下 KD 树会退化到 O(n)，因为回溯过程能剪掉的分支越来越少。\n\n### Ball 树：更适合中等维度\n\nBall 树（ball tree）把数据划分为嵌套的超球体，而不是与坐标轴对齐的方盒。每个节点定义一个球（球心 + 半径），包含该子树中的所有点。\n\n相对 KD 树的优势：\n- 在中等维度（最高约 50 维）下表现更好\n- 能处理非轴对齐的结构\n- 更紧致的包围体意味着搜索时能剪掉更多分支\n\nKD 树和 ball 树都是精确算法。对于真正大规模的搜索（数百万个点、数百个维度），则改用近似最近邻方法（HNSW、IVF、乘积量化）。这些内容在 Phase 1 第 14 课中讲解。\n\n### 惰性学习与积极学习\n\nKNN 是惰性学习器（lazy learner）：训练时不做任何工作，所有计算都发生在预测时。大多数其他算法（线性回归、SVM、神经网络）是积极学习器（eager learner）：在训练时进行大量计算以构建一个紧凑的模型，之后的预测则很快。\n\n| 方面 | 惰性（KNN） | 积极（SVM、神经网络） |\n|--------|------------|------------------------|\n| 训练时间 | O(1)，只需存储数据 | O(n * epochs) |\n| 预测时间 | 每次查询 O(n * d) | O(d) 或 O(参数量) |\n| 预测时的内存 | 存储整个训练集 | 仅存储模型参数 |\n| 适应新数据 | 即时添加数据点 | 重新训练模型 |\n| 决策边界 | 隐式，即时计算 | 显式，训练后固定 |\n\n惰性学习的理想场景：\n- 数据集频繁变化（增删数据点无需重新训练）\n- 只需为极少量查询做预测\n- 希望训练时间为零\n- 数据集足够小，暴力搜索足够快\n\n### 用于回归的 KNN\n\nKNN 做回归时不再是多数投票，而是对 K 个邻居的目标值取平均。\n\n```\nprediction = (1/K) * sum(y_i for i in K nearest neighbors)\n\nOr with distance weighting:\nprediction = sum(w_i * y_i) / sum(w_i)\nwhere w_i = 1 / distance_i\n```\n\nKNN 回归产生分段常数（加权时为分段平滑）的预测。它无法外推到训练数据范围之外。如果训练目标值全都介于 0 到 100 之间，KNN 永远不会预测出 200。\n\n```figure\nknn-smoothness\n```\n\n## 从零实现\n\n### 第 1 步：距离函数\n\n实现 L1、L2、余弦和 Minkowski 距离。这些直接对接 Phase 1 第 14 课。\n\n```python\nimport math\n\ndef l2_distance(a, b):\n    return math.sqrt(sum((ai - bi) ** 2 for ai, bi in zip(a, b)))\n\ndef l1_distance(a, b):\n    return sum(abs(ai - bi) for ai, bi in zip(a, b))\n\ndef cosine_distance(a, b):\n    dot_val = sum(ai * bi for ai, bi in zip(a, b))\n    norm_a = math.sqrt(sum(ai ** 2 for ai in a))\n    norm_b = math.sqrt(sum(bi ** 2 for bi in b))\n    if norm_a == 0 or norm_b == 0:\n        return 1.0\n    return 1.0 - dot_val / (norm_a * norm_b)\n\ndef minkowski_distance(a, b, p=2):\n    if p == float('inf'):\n        return max(abs(ai - bi) for ai, bi in zip(a, b))\n    return sum(abs(ai - bi) ** p for ai, bi in zip(a, b)) ** (1 / p)\n```\n\n### 第 2 步：KNN 分类器与回归器\n\n构建完整的 KNN，支持可配置的 K 值、距离度量和可选的距离加权。\n\n```python\nclass KNN:\n    def __init__(self, k=5, distance_fn=l2_distance, weighted=False,\n                 task=\"classification\"):\n        self.k = k\n        self.distance_fn = distance_fn\n        self.weighted = weighted\n        self.task = task\n        self.X_train = None\n        self.y_train = None\n\n    def fit(self, X, y):\n        self.X_train = X\n        self.y_train = y\n\n    def predict(self, X):\n        return [self._predict_one(x) for x in X]\n```\n\n### 第 3 步：用于高效搜索的 KD 树\n\n从零构建一棵 KD 树，在每个维度的中位数处递归切分。\n\n```python\nclass KDTree:\n    def __init__(self, X, indices=None, depth=0):\n        # Recursively partition the data\n        self.axis = depth % len(X[0])\n        # Split on median of the current axis\n        ...\n\n    def query(self, point, k=1):\n        # Traverse to leaf, then backtrack\n        ...\n```\n\n完整实现（含所有辅助方法和演示）见 `code/knn.py`。\n\n### 第 4 步：特征缩放\n\nKNN 必须做特征缩放，因为距离对特征的量级很敏感。取值范围 0 到 1000 的特征会压倒取值范围 0 到 1 的特征。\n\n```python\ndef standardize(X):\n    n = len(X)\n    d = len(X[0])\n    means = [sum(X[i][j] for i in range(n)) / n for j in range(d)]\n    stds = [\n        max(1e-10, (sum((X[i][j] - means[j]) ** 2 for i in range(n)) / n) ** 0.5)\n        for j in range(d)\n    ]\n    return [[((X[i][j] - means[j]) / stds[j]) for j in range(d)] for i in range(n)], means, stds\n```\n\n## 生产实践\n\n使用 scikit-learn：\n\n```python\nfrom sklearn.neighbors import KNeighborsClassifier\nfrom sklearn.preprocessing import StandardScaler\nfrom sklearn.pipeline import Pipeline\n\nclf = Pipeline([\n    (\"scaler\", StandardScaler()),\n    (\"knn\", KNeighborsClassifier(n_neighbors=5, metric=\"euclidean\")),\n])\nclf.fit(X_train, y_train)\nprint(f\"Accuracy: {clf.score(X_test, y_test):.4f}\")\n```\n\n当数据集足够大且维度足够低时，scikit-learn 会自动使用 KD 树或 ball 树。对于高维数据，它会回退到暴力搜索。你可以通过 `algorithm` 参数控制这一行为。\n\n对于大规模最近邻搜索（数百万向量），使用 FAISS、Annoy 或向量数据库：\n\n```python\nimport faiss\n\nindex = faiss.IndexFlatL2(dimension)\nindex.add(embeddings)\ndistances, indices = index.search(query_vectors, k=5)\n```\n\n## 练习\n\n1. 在一个含 3 个类别的二维数据集上实现 KNN 分类。绘制 K=1、K=5、K=15 和 K=N 时的决策边界，观察从过拟合到欠拟合的转变。\n\n2. 分别在 2、5、10、50、100 和 500 维空间中生成 1000 个随机点。对每个维度，计算成对距离的最大值与最小值之比。绘制该比值随维度变化的曲线，直观展示维度灾难。\n\n3. 在一个文本分类问题上（使用 TF-IDF 向量）比较 L1、L2 和余弦距离下的 KNN。哪个度量准确率最高？为什么余弦在文本任务上往往胜出？\n\n4. 实现一棵 KD 树，在 2 维、10 维和 50 维下，针对 1k、10k 和 100k 个点的数据集测量查询时间，并与暴力搜索对比。在多少维时 KD 树不再比暴力搜索更快？\n\n5. 为 y = sin(x) + noise 构建一个加权 KNN 回归器。在 K=3、10、30 时与不加权的 KNN 比较，证明加权能产生更平滑的预测，尤其是在 K 较大时。\n\n## 关键术语\n\n| 术语 | 真正含义 |\n|------|----------------------|\n| K 近邻 | 非参数算法，通过查找离查询点最近的 K 个训练点来做预测 |\n| 惰性学习 | 训练时不做任何计算，所有工作都发生在预测时。KNN 是典型例子 |\n| 积极学习 | 在训练时进行大量计算以构建紧凑模型。大多数 ML 算法都是积极学习 |\n| 维度灾难 | 高维下距离趋同、邻域扩展到覆盖大部分空间，导致 KNN 失效 |\n| KD 树 | 沿特征轴递归划分空间的二叉树。低维下查询为 O(log n) |\n| Ball 树 | 由嵌套超球体构成的树。在中等维度（最高约 50 维）下优于 KD 树 |\n| 加权 KNN | 邻居按距离的倒数加权。更近的邻居对预测的影响更大 |\n| 特征缩放 | 把特征归一化到可比较的范围。KNN 等基于距离的方法必不可少 |\n| 多数投票 | 通过统计 K 个邻居中最常见的类别来分类 |\n| 暴力搜索 | 计算到每个训练点的距离。每次查询 O(n*d)。精确但在 n 很大时很慢 |\n| 近似最近邻 | 一类算法（HNSW、LSH、IVF），以远快于精确搜索的速度找到近似最近的点 |\n| Voronoi 图 | 对空间的一种划分，每个区域包含所有离某个训练点比离其他任何训练点都近的点。K=1 的 KNN 产生 Voronoi 边界 |\n\n## 延伸阅读\n\n- [Cover & Hart: Nearest Neighbor Pattern Classification (1967)](https://ieeexplore.ieee.org/document/1053964) - KNN 的奠基性论文，证明其错误率至多是贝叶斯最优错误率的两倍\n- [Friedman, Bentley, Finkel: An Algorithm for Finding Best Matches in Logarithmic Expected Time (1977)](https://dl.acm.org/doi/10.1145/355744.355745) - KD 树的原始论文\n- [Beyer et al.: When Is \"Nearest Neighbor\" Meaningful? (1999)](https://link.springer.com/chapter/10.1007/3-540-49257-7_15) - 对最近邻维度灾难的形式化分析\n- [scikit-learn Nearest Neighbors documentation](https://scikit-learn.org/stable/modules/neighbors.html) - 包含算法选择建议的实用指南\n- [FAISS: A Library for Efficient Similarity Search](https://github.com/facebookresearch/faiss) - Meta 推出的库，支持十亿级近似最近邻搜索\n","quizEn":null,"quizZh":[{"id":"knn-pre-1","stage":"pre","question":"KNN 被称为「惰性学习器」（lazy learner），这是什么意思？","options":["它在训练期间收敛缓慢","它在训练时不做任何计算，所有计算都发生在预测时","它使用了简化版的损失函数","它只适用于小数据集"],"correct":1,"explanation":"惰性学习意味着 KNN 只存储训练数据，在「训练」期间不做任何工作。所有计算（距离计算、投票）都发生在请求预测的时候。"},{"id":"knn-pre-2","stage":"pre","question":"为什么特征缩放对 KNN 至关重要？","options":["不做缩放 KNN 就无法处理负数","距离计算会被取值范围更大的特征主导，必须缩放才能公平比较","特征缩放能减少所需邻居的数量","KNN 使用梯度下降，需要归一化的输入"],"correct":1,"explanation":"KNN 依赖距离。取值范围 0-1000 的特征会在距离计算中压倒取值范围 0-1 的特征。缩放能把所有特征放到可比较的范围内。"},{"id":"knn-post-1","stage":"post","question":"对于 100 维空间中均匀分布的随机点，最大距离与最小距离之比会发生什么变化？","options":["比值急剧增大，使邻居之间区分更明显","比值趋近于 1，使所有点彼此之间几乎等距","与 2 维时保持相同","因数值溢出而变为负数"],"correct":1,"explanation":"这就是维度灾难。在高维空间中距离趋同：max_dist / min_dist 趋近于 1。当所有点都等距时，「最近」就失去了意义。"},{"id":"knn-post-2","stage":"post","question":"比较以 TF-IDF 向量表示的文本文档时，哪种距离度量最合适？","options":["L2（欧氏）距离","L1（曼哈顿）距离","余弦距离","Chebyshev 距离"],"correct":2,"explanation":"余弦距离衡量向量之间的夹角，忽略模长。对文本来说，文档长度（模长）是噪声——方向才承载语义。在文本任务上余弦距离的表现稳定优于 L1/L2。"},{"id":"knn-post-3","stage":"post","question":"当 K 从 1 增大到 N（整个数据集的规模）时，KNN 的决策边界会发生什么变化？","options":["边界变得更复杂、更精细","无论 K 取多少，边界都保持不变","边界逐渐变平滑，最终对每个点都预测多数类","边界变成圆形"],"correct":2,"explanation":"K=1 会产生跟随每个点的锯齿状边界（过拟合）。随着 K 增大，边界逐渐平滑。K=N 时每次查询都会考虑所有点，总是预测多数类（偏差最大）。"}],"code":[{"name":"knn.py","lang":"python","content":"import math\nimport random\n\n\ndef l2_distance(a, b):\n    return math.sqrt(sum((ai - bi) ** 2 for ai, bi in zip(a, b)))\n\n\ndef l1_distance(a, b):\n    return sum(abs(ai - bi) for ai, bi in zip(a, b))\n\n\ndef cosine_distance(a, b):\n    dot_val = sum(ai * bi for ai, bi in zip(a, b))\n    norm_a = math.sqrt(sum(ai ** 2 for ai in a))\n    norm_b = math.sqrt(sum(bi ** 2 for bi in b))\n    if norm_a == 0 or norm_b == 0:\n        return 1.0\n    return 1.0 - dot_val / (norm_a * norm_b)\n\n\ndef minkowski_distance(a, b, p=2):\n    if p == float(\"inf\"):\n        return max(abs(ai - bi) for ai, bi in zip(a, b))\n    return sum(abs(ai - bi) ** p for ai, bi in zip(a, b)) ** (1 / p)\n\n\ndef standardize(X):\n    n = len(X)\n    d = len(X[0])\n    means = [sum(X[i][j] for i in range(n)) / n for j in range(d)]\n    stds = [\n        max(\n            1e-10,\n            (sum((X[i][j] - means[j]) ** 2 for i in range(n)) / n) ** 0.5,\n        )\n        for j in range(d)\n    ]\n    X_scaled = [\n        [(X[i][j] - means[j]) / stds[j] for j in range(d)] for i in range(n)\n    ]\n    return X_scaled, means, stds\n\n\ndef apply_standardize(X, means, stds):\n    return [[(x[j] - means[j]) / stds[j] for j in range(len(x))] for x in X]\n\n\nclass KNN:\n    def __init__(self, k=5, distance_fn=l2_distance, weighted=False,\n                 task=\"classification\"):\n        self.k = k\n        self.distance_fn = distance_fn\n        self.weighted = weighted\n        self.task = task\n        self.X_train = None\n        self.y_train = None\n\n    def fit(self, X, y):\n        self.X_train = list(X)\n        self.y_train = list(y)\n\n    def predict(self, X):\n        return [self._predict_one(x) for x in X]\n\n    def _predict_one(self, x):\n        distances = []\n        for i in range(len(self.X_train)):\n            d = self.distance_fn(x, self.X_train[i])\n            distances.append((d, self.y_train[i]))\n        distances.sort(key=lambda pair: pair[0])\n        neighbors = distances[: self.k]\n\n        if self.task == \"classification\":\n            return self._classify(neighbors)\n        return self._regress(neighbors)\n\n    def _classify(self, neighbors):\n        if self.weighted:\n            votes = {}\n            for dist, label in neighbors:\n                w = 1.0 / (dist + 1e-10)\n                votes[label] = votes.get(label, 0) + w\n        else:\n            votes = {}\n            for _, label in neighbors:\n                votes[label] = votes.get(label, 0) + 1\n        return max(votes, key=votes.get)\n\n    def _regress(self, neighbors):\n        if self.weighted:\n            w_sum = 0.0\n            val_sum = 0.0\n            for dist, val in neighbors:\n                w = 1.0 / (dist + 1e-10)\n                val_sum += w * val\n                w_sum += w\n            return val_sum / w_sum if w_sum > 0 else 0.0\n        return sum(val for _, val in neighbors) / len(neighbors)\n\n    def predict_with_neighbors(self, x):\n        distances = []\n        for i in range(len(self.X_train)):\n            d = self.distance_fn(x, self.X_train[i])\n            distances.append((d, i, self.y_train[i]))\n        distances.sort(key=lambda t: t[0])\n        neighbors = distances[: self.k]\n        prediction = self._predict_one(x)\n        return prediction, neighbors\n\n\nclass KDNode:\n    def __init__(self, point, index, axis, left=None, right=None):\n        self.point = point\n        self.index = index\n        self.axis = axis\n        self.left = left\n        self.right = right\n\n\nclass KDTree:\n    def __init__(self, X):\n        self.dim = len(X[0])\n        indexed = [(X[i], i) for i in range(len(X))]\n        self.root = self._build(indexed, depth=0)\n\n    def _build(self, points, depth):\n        if not points:\n            return None\n        axis = depth % self.dim\n        points.sort(key=lambda p: p[0][axis])\n        mid = len(points) // 2\n        return KDNode(\n            point=points[mid][0],\n            index=points[mid][1],\n            axis=axis,\n            left=self._build(points[:mid], depth + 1),\n            right=self._build(points[mid + 1 :], depth + 1),\n        )\n\n    def query(self, point, k=1):\n        best = []\n        self._search(self.root, point, k, best)\n        best.sort(key=lambda x: x[0])\n        return best\n\n    def _search(self, node, point, k, best):\n        if node is None:\n            return\n\n        dist = l2_distance(point, node.point)\n\n        if len(best) < k:\n            best.append((dist, node.index, node.point))\n            best.sort(key=lambda x: x[0])\n        elif dist < best[-1][0]:\n            best[-1] = (dist, node.index, node.point)\n            best.sort(key=lambda x: x[0])\n\n        axis = node.axis\n        diff = point[axis] - node.point[axis]\n\n        if diff <= 0:\n            first, second = node.left, node.right\n        else:\n            first, second = node.right, node.left\n\n        self._search(first, point, k, best)\n\n        if len(best) < k or abs(diff) < best[-1][0]:\n            self._search(second, point, k, best)\n\n\ndef accuracy(y_true, y_pred):\n    correct = sum(1 for a, b in zip(y_true, y_pred) if a == b)\n    return correct / len(y_true)\n\n\ndef mse(y_true, y_pred):\n    return sum((a - b) ** 2 for a, b in zip(y_true, y_pred)) / len(y_true)\n\n\ndef generate_classification_data(n_samples=200, n_classes=3, seed=42):\n    random.seed(seed)\n    X = []\n    y = []\n    centers = [\n        [1.0, 1.0],\n        [-1.0, -1.0],\n        [1.0, -1.0],\n    ]\n    for _ in range(n_samples):\n        c = random.randint(0, n_classes - 1)\n        x1 = centers[c][0] + random.gauss(0, 0.5)\n        x2 = centers[c][1] + random.gauss(0, 0.5)\n        X.append([x1, x2])\n        y.append(c)\n    return X, y\n\n\ndef generate_regression_data(n_samples=200, seed=42):\n    random.seed(seed)\n    X = []\n    y = []\n    for _ in range(n_samples):\n        x = random.uniform(-3, 3)\n        target = math.sin(x) + random.gauss(0, 0.15)\n        X.append([x])\n        y.append(target)\n    return X, y\n\n\ndef generate_high_dim_data(n_samples=500, n_dims=2, seed=42):\n    random.seed(seed)\n    X = []\n    y = []\n    for _ in range(n_samples):\n        point = [random.uniform(0, 1) for _ in range(n_dims)]\n        label = 1 if sum(point[:2]) > 1.0 else 0\n        X.append(point)\n        y.append(label)\n    return X, y\n\n\ndef train_test_split(X, y, test_ratio=0.2, seed=42):\n    random.seed(seed)\n    n = len(X)\n    indices = list(range(n))\n    random.shuffle(indices)\n    split = int(n * (1 - test_ratio))\n    train_idx = indices[:split]\n    test_idx = indices[split:]\n    return (\n        [X[i] for i in train_idx],\n        [y[i] for i in train_idx],\n        [X[i] for i in test_idx],\n        [y[i] for i in test_idx],\n    )\n\n\ndef demo_basic_knn():\n    print(\"=\" * 65)\n    print(\"KNN CLASSIFICATION: THE BASICS\")\n    print(\"=\" * 65)\n    print()\n\n    X, y = generate_classification_data(200, seed=42)\n    X_train, y_train, X_test, y_test = train_test_split(X, y)\n\n    print(f\"  Dataset: {len(X)} samples, 2 features, 3 classes\")\n    print(f\"  Train: {len(X_train)}  Test: {len(X_test)}\")\n    print()\n\n    k_values = [1, 3, 5, 7, 11, 15, 25, 50]\n    print(f\"  {'K':>6s}  {'Train Acc':>10s}  {'Test Acc':>10s}\")\n    print(f\"  {'-' * 6}  {'-' * 10}  {'-' * 10}\")\n\n    for k in k_values:\n        knn = KNN(k=k, task=\"classification\")\n        knn.fit(X_train, y_train)\n        train_acc = accuracy(y_train, knn.predict(X_train))\n        test_acc = accuracy(y_test, knn.predict(X_test))\n        print(f\"  {k:>6d}  {train_acc:>10.4f}  {test_acc:>10.4f}\")\n\n    print()\n    print(\"  K=1: perfect training accuracy (memorization), lower test accuracy.\")\n    print(\"  Increasing K smooths the decision boundary.\")\n    print()\n\n\ndef demo_distance_metrics():\n    print(\"=\" * 65)\n    print(\"DISTANCE METRICS: SAME DATA, DIFFERENT NEIGHBORS\")\n    print(\"=\" * 65)\n    print()\n\n    X, y = generate_classification_data(200, seed=42)\n    X_scaled, means, stds = standardize(X)\n    X_train, y_train, X_test, y_test = train_test_split(X_scaled, y)\n\n    metrics = [\n        (\"L2 (Euclidean)\", l2_distance),\n        (\"L1 (Manhattan)\", l1_distance),\n        (\"Cosine\", cosine_distance),\n    ]\n\n    k = 5\n    print(f\"  K = {k}, features standardized\")\n    print()\n    print(f\"  {'Metric':<20s}  {'Test Accuracy':>14s}\")\n    print(f\"  {'-' * 20}  {'-' * 14}\")\n\n    for name, dist_fn in metrics:\n        knn = KNN(k=k, distance_fn=dist_fn, task=\"classification\")\n        knn.fit(X_train, y_train)\n        test_acc = accuracy(y_test, knn.predict(X_test))\n        print(f\"  {name:<20s}  {test_acc:>14.4f}\")\n\n    print()\n\n    query = X_test[0]\n    print(f\"  Query point: [{query[0]:.3f}, {query[1]:.3f}]\")\n    print(f\"  True label: {y_test[0]}\")\n    print()\n\n    for name, dist_fn in metrics:\n        knn = KNN(k=k, distance_fn=dist_fn, task=\"classification\")\n        knn.fit(X_train, y_train)\n        pred, neighbors = knn.predict_with_neighbors(query)\n        print(f\"  {name}: prediction = {pred}\")\n        for dist, idx, label in neighbors:\n            print(f\"    neighbor idx={idx}, label={label}, dist={dist:.4f}\")\n        print()\n\n\ndef demo_weighted_knn():\n    print(\"=\" * 65)\n    print(\"WEIGHTED vs UNWEIGHTED KNN\")\n    print(\"=\" * 65)\n    print()\n\n    X, y = generate_classification_data(200, seed=42)\n    X_scaled, _, _ = standardize(X)\n    X_train, y_train, X_test, y_test = train_test_split(X_scaled, y)\n\n    k_values = [3, 7, 15, 25]\n    print(f\"  {'K':>6s}  {'Unweighted':>12s}  {'Weighted':>12s}  {'Diff':>8s}\")\n    print(f\"  {'-' * 6}  {'-' * 12}  {'-' * 12}  {'-' * 8}\")\n\n    for k in k_values:\n        knn_uw = KNN(k=k, weighted=False, task=\"classification\")\n        knn_w = KNN(k=k, weighted=True, task=\"classification\")\n        knn_uw.fit(X_train, y_train)\n        knn_w.fit(X_train, y_train)\n        acc_uw = accuracy(y_test, knn_uw.predict(X_test))\n        acc_w = accuracy(y_test, knn_w.predict(X_test))\n        diff = acc_w - acc_uw\n        print(f\"  {k:>6d}  {acc_uw:>12.4f}  {acc_w:>12.4f}  {diff:>+8.4f}\")\n\n    print()\n    print(\"  Weighted KNN is less sensitive to large K values.\")\n    print(\"  Distant neighbors contribute less, so increasing K is safer.\")\n    print()\n\n\ndef demo_regression():\n    print(\"=\" * 65)\n    print(\"KNN REGRESSION: APPROXIMATING sin(x)\")\n    print(\"=\" * 65)\n    print()\n\n    X, y = generate_regression_data(200, seed=42)\n    X_train, y_train, X_test, y_test = train_test_split(X, y)\n\n    k_values = [1, 3, 5, 10, 20, 50]\n    print(f\"  Target: y = sin(x) + noise\")\n    print(f\"  Train: {len(X_train)}  Test: {len(X_test)}\")\n    print()\n    print(f\"  {'K':>6s}  {'Unweighted MSE':>16s}  {'Weighted MSE':>14s}\")\n    print(f\"  {'-' * 6}  {'-' * 16}  {'-' * 14}\")\n\n    for k in k_values:\n        knn_uw = KNN(k=k, task=\"regression\", weighted=False)\n        knn_w = KNN(k=k, task=\"regression\", weighted=True)\n        knn_uw.fit(X_train, y_train)\n        knn_w.fit(X_train, y_train)\n        mse_uw = mse(y_test, knn_uw.predict(X_test))\n        mse_w = mse(y_test, knn_w.predict(X_test))\n        print(f\"  {k:>6d}  {mse_uw:>16.6f}  {mse_w:>14.6f}\")\n\n    print()\n    print(\"  K=1 overfits (follows noise). Large K underfits (over-smooths).\")\n    print(\"  Weighted KNN smooths predictions while respecting local structure.\")\n    print()\n\n    knn = KNN(k=5, task=\"regression\", weighted=True)\n    knn.fit(X_train, y_train)\n\n    print(\"  Sample predictions (K=5, weighted):\")\n    print(f\"  {'x':>8s}  {'True y':>8s}  {'Pred y':>8s}  {'Error':>8s}\")\n    print(f\"  {'-' * 8}  {'-' * 8}  {'-' * 8}  {'-' * 8}\")\n    for i in range(min(10, len(X_test))):\n        pred = knn.predict([X_test[i]])[0]\n        err = abs(y_test[i] - pred)\n        print(f\"  {X_test[i][0]:>8.3f}  {y_test[i]:>8.3f}  {pred:>8.3f}  {err:>8.3f}\")\n    print()\n\n\ndef demo_curse_of_dimensionality():\n    print(\"=\" * 65)\n    print(\"CURSE OF DIMENSIONALITY\")\n    print(\"=\" * 65)\n    print()\n\n    dims = [2, 5, 10, 20, 50, 100]\n    n_points = 200\n\n    print(\"  Part 1: Distance ratio convergence\")\n    print(f\"  {n_points} random uniform points in [0, 1]^d\")\n    print()\n    print(f\"  {'Dimensions':>12s}  {'Max/Min dist':>14s}  {'Mean dist':>10s}  {'Std dist':>10s}\")\n    print(f\"  {'-' * 12}  {'-' * 14}  {'-' * 10}  {'-' * 10}\")\n\n    for d in dims:\n        random.seed(42)\n        points = [[random.uniform(0, 1) for _ in range(d)] for _ in range(n_points)]\n\n        distances = []\n        sample_size = min(500, n_points * (n_points - 1) // 2)\n        for _ in range(sample_size):\n            i = random.randint(0, n_points - 1)\n            j = random.randint(0, n_points - 1)\n            if i != j:\n                distances.append(l2_distance(points[i], points[j]))\n\n        if distances:\n            max_d = max(distances)\n            min_d = min(d_val for d_val in distances if d_val > 0)\n            mean_d = sum(distances) / len(distances)\n            std_d = (sum((d_val - mean_d) ** 2 for d_val in distances) / len(distances)) ** 0.5\n            ratio = max_d / min_d if min_d > 0 else float(\"inf\")\n            print(f\"  {d:>12d}  {ratio:>14.4f}  {mean_d:>10.4f}  {std_d:>10.4f}\")\n\n    print()\n    print(\"  As dimensions grow, max/min ratio shrinks toward 1.\")\n    print(\"  All points become equally distant. 'Nearest' loses meaning.\")\n    print()\n\n    print(\"  Part 2: KNN accuracy vs dimensionality\")\n    print(f\"  Binary classification: label = 1 if x[0] + x[1] > 1, else 0\")\n    print(f\"  Extra dimensions are pure noise.\")\n    print()\n    print(f\"  {'Dimensions':>12s}  {'K=5 Acc':>10s}  {'K=15 Acc':>10s}\")\n    print(f\"  {'-' * 12}  {'-' * 10}  {'-' * 10}\")\n\n    for d in [2, 5, 10, 20, 50]:\n        X, y = generate_high_dim_data(400, n_dims=d, seed=42)\n        X_scaled, _, _ = standardize(X)\n        X_train, y_train, X_test, y_test = train_test_split(X_scaled, y)\n\n        knn5 = KNN(k=5, task=\"classification\")\n        knn15 = KNN(k=15, task=\"classification\")\n        knn5.fit(X_train, y_train)\n        knn15.fit(X_train, y_train)\n        acc5 = accuracy(y_test, knn5.predict(X_test))\n        acc15 = accuracy(y_test, knn15.predict(X_test))\n        print(f\"  {d:>12d}  {acc5:>10.4f}  {acc15:>10.4f}\")\n\n    print()\n    print(\"  Accuracy degrades as noisy dimensions increase.\")\n    print(\"  The signal (first 2 dims) gets drowned by noise dimensions.\")\n    print()\n\n\ndef demo_kdtree():\n    print(\"=\" * 65)\n    print(\"KD-TREE: EFFICIENT NEAREST NEIGHBOR SEARCH\")\n    print(\"=\" * 65)\n    print()\n\n    random.seed(42)\n    sizes = [100, 500, 1000, 5000]\n\n    print(f\"  2D data, finding 5 nearest neighbors\")\n    print()\n    print(f\"  {'N points':>10s}  {'Brute force':>14s}  {'KD-tree':>14s}  {'Speedup':>10s}\")\n    print(f\"  {'-' * 10}  {'-' * 14}  {'-' * 14}  {'-' * 10}\")\n\n    for n in sizes:\n        X = [[random.uniform(0, 10) for _ in range(2)] for _ in range(n)]\n        query = [5.0, 5.0]\n        k = 5\n\n        import time\n\n        n_queries = 100\n        queries = [[random.uniform(0, 10) for _ in range(2)] for _ in range(n_queries)]\n\n        start = time.time()\n        for q in queries:\n            dists = [(l2_distance(q, X[i]), i) for i in range(n)]\n            dists.sort()\n            _ = dists[:k]\n        brute_time = time.time() - start\n\n        tree = KDTree(X)\n\n        start = time.time()\n        for q in queries:\n            _ = tree.query(q, k=k)\n        kd_time = time.time() - start\n\n        speedup = brute_time / kd_time if kd_time > 0 else float(\"inf\")\n        print(f\"  {n:>10d}  {brute_time:>14.4f}s  {kd_time:>14.4f}s  {speedup:>10.1f}x\")\n\n    print()\n\n    X = [[random.uniform(0, 10) for _ in range(2)] for _ in range(100)]\n    tree = KDTree(X)\n    query = [5.0, 5.0]\n\n    brute = [(l2_distance(query, X[i]), i) for i in range(len(X))]\n    brute.sort()\n    brute_top5 = [(d, idx) for d, idx in brute[:5]]\n\n    kd_top5 = [(d, idx) for d, idx, _ in tree.query(query, k=5)]\n\n    print(\"  Verification (100 points, k=5):\")\n    print(f\"    Brute force: {[(round(d, 4), idx) for d, idx in brute_top5]}\")\n    print(f\"    KD-tree:     {[(round(d, 4), idx) for d, idx in kd_top5]}\")\n    match = set(idx for _, idx in brute_top5) == set(idx for _, idx in kd_top5)\n    print(f\"    Results match: {match}\")\n    print()\n\n\ndef demo_scaling_importance():\n    print(\"=\" * 65)\n    print(\"FEATURE SCALING: WHY IT MATTERS FOR KNN\")\n    print(\"=\" * 65)\n    print()\n\n    random.seed(42)\n    X = []\n    y = []\n    for _ in range(200):\n        age = random.gauss(40, 15)\n        salary = random.gauss(50000, 20000)\n        label = 1 if age > 45 and salary < 40000 else 0\n        X.append([age, salary])\n        y.append(label)\n\n    X_train, y_train, X_test, y_test = train_test_split(X, y)\n\n    knn_raw = KNN(k=5, task=\"classification\")\n    knn_raw.fit(X_train, y_train)\n    acc_raw = accuracy(y_test, knn_raw.predict(X_test))\n\n    X_train_s, means, stds = standardize(X_train)\n    X_test_s = apply_standardize(X_test, means, stds)\n\n    knn_scaled = KNN(k=5, task=\"classification\")\n    knn_scaled.fit(X_train_s, y_train)\n    acc_scaled = accuracy(y_test, knn_scaled.predict(X_test_s))\n\n    print(f\"  Features: age (range ~10-70), salary (range ~10k-90k)\")\n    print()\n    print(f\"  Without scaling: accuracy = {acc_raw:.4f}\")\n    print(f\"  With scaling:    accuracy = {acc_scaled:.4f}\")\n    print()\n\n    query = X_test[0]\n    query_s = X_test_s[0]\n\n    dists_raw = [(l2_distance(query, X_train[i]), i) for i in range(5)]\n    dists_raw.sort()\n    dists_scaled = [(l2_distance(query_s, X_train_s[i]), i) for i in range(5)]\n    dists_scaled.sort()\n\n    print(f\"  Sample distances for first test point:\")\n    print(f\"  Without scaling: {[round(d, 1) for d, _ in dists_raw]}\")\n    print(f\"  With scaling:    {[round(d, 4) for d, _ in dists_scaled]}\")\n    print()\n    print(\"  Unscaled: salary dominates (tens of thousands vs tens of years).\")\n    print(\"  Scaled: both features contribute equally to distance.\")\n    print()\n\n\ndef demo_lazy_vs_eager():\n    print(\"=\" * 65)\n    print(\"LAZY vs EAGER LEARNING: TIMING COMPARISON\")\n    print(\"=\" * 65)\n    print()\n\n    import time\n\n    random.seed(42)\n    sizes = [100, 500, 1000, 5000]\n\n    print(f\"  {'N':>6s}  {'KNN train':>12s}  {'KNN predict':>14s}  {'Total':>10s}\")\n    print(f\"  {'-' * 6}  {'-' * 12}  {'-' * 14}  {'-' * 10}\")\n\n    for n in sizes:\n        X = [[random.gauss(0, 1) for _ in range(5)] for _ in range(n)]\n        y = [random.choice([0, 1]) for _ in range(n)]\n\n        n_test = min(50, n // 5)\n        X_test_local = [[random.gauss(0, 1) for _ in range(5)] for _ in range(n_test)]\n\n        knn = KNN(k=5, task=\"classification\")\n\n        start = time.time()\n        knn.fit(X, y)\n        train_time = time.time() - start\n\n        start = time.time()\n        knn.predict(X_test_local)\n        pred_time = time.time() - start\n\n        total = train_time + pred_time\n        print(f\"  {n:>6d}  {train_time:>12.6f}s  {pred_time:>14.6f}s  {total:>10.6f}s\")\n\n    print()\n    print(\"  KNN training is O(1): just store the data.\")\n    print(\"  KNN prediction is O(n*d) per query: compute all distances.\")\n    print(\"  For eager learners (neural nets), the pattern is reversed.\")\n    print()\n\n\ndef demo_minkowski_family():\n    print(\"=\" * 65)\n    print(\"MINKOWSKI DISTANCE FAMILY\")\n    print(\"=\" * 65)\n    print()\n\n    a = [1.0, 2.0, 3.0]\n    b = [4.0, 0.0, 6.0]\n\n    p_values = [1, 1.5, 2, 3, 5, 10, float(\"inf\")]\n    print(f\"  a = {a}\")\n    print(f\"  b = {b}\")\n    print()\n    print(f\"  {'p':>8s}  {'Distance':>12s}  {'Name':>15s}\")\n    print(f\"  {'-' * 8}  {'-' * 12}  {'-' * 15}\")\n\n    for p in p_values:\n        d = minkowski_distance(a, b, p)\n        if p == 1:\n            name = \"Manhattan (L1)\"\n        elif p == 2:\n            name = \"Euclidean (L2)\"\n        elif p == float(\"inf\"):\n            name = \"Chebyshev (Linf)\"\n        else:\n            name = f\"Lp (p={p})\"\n        p_str = \"inf\" if p == float(\"inf\") else str(p)\n        print(f\"  {p_str:>8s}  {d:>12.4f}  {name:>15s}\")\n\n    print()\n    print(\"  As p increases, the distance is dominated by the largest component difference.\")\n    print(\"  L-inf <= L2 <= L1 always holds.\")\n    print()\n\n\ndef demo_k_selection():\n    print(\"=\" * 65)\n    print(\"SELECTING K: CROSS-VALIDATION APPROACH\")\n    print(\"=\" * 65)\n    print()\n\n    X, y = generate_classification_data(300, seed=42)\n\n    n = len(X)\n    random.seed(42)\n    indices = list(range(n))\n    random.shuffle(indices)\n\n    n_folds = 5\n    fold_size = n // n_folds\n\n    k_values = [1, 3, 5, 7, 9, 11, 15, 21, 31]\n\n    print(f\"  {n_folds}-fold cross-validation on {n} samples\")\n    print()\n    print(f\"  {'K':>6s}  {'Mean Acc':>10s}  {'Std Acc':>10s}  {'Visual':>20s}\")\n    print(f\"  {'-' * 6}  {'-' * 10}  {'-' * 10}  {'-' * 20}\")\n\n    best_k = 1\n    best_mean = 0.0\n\n    for k in k_values:\n        fold_accs = []\n\n        for fold in range(n_folds):\n            val_start = fold * fold_size\n            val_end = val_start + fold_size\n            val_idx = indices[val_start:val_end]\n            train_idx = indices[:val_start] + indices[val_end:]\n\n            X_tr = [X[i] for i in train_idx]\n            y_tr = [y[i] for i in train_idx]\n            X_val = [X[i] for i in val_idx]\n            y_val = [y[i] for i in val_idx]\n\n            knn = KNN(k=k, task=\"classification\")\n            knn.fit(X_tr, y_tr)\n            acc_val = accuracy(y_val, knn.predict(X_val))\n            fold_accs.append(acc_val)\n\n        mean_acc = sum(fold_accs) / len(fold_accs)\n        std_acc = (sum((a - mean_acc) ** 2 for a in fold_accs) / len(fold_accs)) ** 0.5\n\n        bar_len = int(mean_acc * 20)\n        bar = \"#\" * bar_len\n\n        if mean_acc > best_mean:\n            best_mean = mean_acc\n            best_k = k\n\n        print(f\"  {k:>6d}  {mean_acc:>10.4f}  {std_acc:>10.4f}  {bar}\")\n\n    print()\n    print(f\"  Best K = {best_k} with mean accuracy = {best_mean:.4f}\")\n    print()\n\n\ndef print_summary():\n    print()\n    print(\"=\" * 65)\n    print(\"SUMMARY\")\n    print(\"=\" * 65)\n    print()\n    print(\"  1. KNN is lazy: zero training, all work at prediction time.\")\n    print(\"  2. K controls bias-variance: small K overfits, large K underfits.\")\n    print(\"  3. Distance metric choice matters. L2 is default, cosine for text.\")\n    print(\"  4. Always scale features. Unscaled features distort distances.\")\n    print(\"  5. Weighted KNN reduces sensitivity to K by down-weighting distant neighbors.\")\n    print(\"  6. Curse of dimensionality: KNN degrades beyond ~20-50 dimensions.\")\n    print(\"  7. KD-trees speed up search in low dimensions. Ball trees for moderate.\")\n    print(\"  8. KNN is the same algorithm behind vector databases and RAG retrieval.\")\n    print()\n\n\nif __name__ == \"__main__\":\n    demo_basic_knn()\n    demo_distance_metrics()\n    demo_weighted_knn()\n    demo_regression()\n    demo_minkowski_family()\n    demo_curse_of_dimensionality()\n    demo_scaling_importance()\n    demo_kdtree()\n    demo_lazy_vs_eager()\n    demo_k_selection()\n    print_summary()\n","runnable":true}],"challenge":{"titleZh":"从零实现 KNN：分类与回归","titleEn":"Build KNN from Scratch: Classify and Regress","promptZh":"K 近邻（KNN）没有训练阶段：把整个训练集存下来，预测时找出离查询点最近的 K 个邻居，让它们投票或求平均。本挑战请你用纯 Python 实现这套「惰性学习」的四个核心函数。\n\n1. `l2_distance(a, b)` —— 欧氏（L2）距离：`d(a, b) = sqrt(sum((a_i - b_i)^2))`。`a`、`b` 是等长数值向量。\n\n2. `k_nearest(query, X_train, k)` —— 返回 `X_train` 中离 `query` 最近的 `k` 个点的下标列表，按距离升序排列。规则：先用 `l2_distance` 计算 query 到每个训练点的距离，排序，取前 `k` 个的下标。距离并列时，下标小的排在前面（即按 `(距离, 下标)` 排序）。\n\n3. `knn_classify(query, X_train, y_train, k)` —— 多数投票分类。取 `k` 个最近邻的标签，返回出现次数最多的标签。若票数并列，返回「最小」的标签（用 `min` 在并列标签上选）。`y_train` 的标签可比较（数字或字符串）。\n\n4. `knn_regress(query, X_train, y_train, k, weighted=False)` —— KNN 回归。\n   - `weighted=False`：返回 `k` 个最近邻目标值的算术平均。\n   - `weighted=True`：按距离反比加权平均，`w_i = 1 / (distance_i + 1e-10)`，返回 `sum(w_i * y_i) / sum(w_i)`。`1e-10` 防止查询点恰好与某训练点重合时除零。\n\n要求：仅用 Python 标准库（可 `import math`），不要用 numpy/sklearn。`knn_classify` 和 `knn_regress` 必须复用 `k_nearest`，而 `k_nearest` 必须复用 `l2_distance`。","promptEn":"K-nearest neighbors (KNN) has no training phase: you store the whole training set, then at prediction time you find the K closest neighbors of a query point and let them vote or average. In this challenge you implement the four core functions of this \"lazy learner\" in pure Python.\n\n1. `l2_distance(a, b)` — Euclidean (L2) distance: `d(a, b) = sqrt(sum((a_i - b_i)^2))`. `a` and `b` are equal-length numeric vectors.\n\n2. `k_nearest(query, X_train, k)` — return the indices of the `k` points in `X_train` closest to `query`, sorted by ascending distance. Rule: use `l2_distance` to measure query-to-point distances, sort, and take the first `k` indices. Break ties on distance by smaller index (i.e. sort by `(distance, index)`).\n\n3. `knn_classify(query, X_train, y_train, k)` — majority-vote classification. Take the labels of the `k` nearest neighbors and return the most frequent label. On a vote tie, return the \"smallest\" tied label (use `min` over the tied labels). Labels in `y_train` are comparable (numbers or strings).\n\n4. `knn_regress(query, X_train, y_train, k, weighted=False)` — KNN regression.\n   - `weighted=False`: return the plain arithmetic mean of the `k` nearest neighbors' targets.\n   - `weighted=True`: return the inverse-distance weighted average, `w_i = 1 / (distance_i + 1e-10)`, i.e. `sum(w_i * y_i) / sum(w_i)`. The `1e-10` prevents division by zero when the query exactly matches a training point.\n\nRequirements: use only the Python standard library (`import math` is fine), no numpy/sklearn. `knn_classify` and `knn_regress` must reuse `k_nearest`, and `k_nearest` must reuse `l2_distance`.","starter":"import math\n\n\ndef l2_distance(a, b):\n    \"\"\"Euclidean (L2) distance between two equal-length vectors.\n\n    d(a, b) = sqrt(sum((a_i - b_i) ** 2)).\n\n    Args:\n        a: list of numbers.\n        b: list of numbers, same length as a.\n\n    Returns:\n        float: the L2 distance.\n    \"\"\"\n    # TODO: sum the squared differences component-wise, then take the sqrt.\n    raise NotImplementedError\n\n\ndef k_nearest(query, X_train, k):\n    \"\"\"Indices of the k training points closest to query.\n\n    Args:\n        query: the query vector.\n        X_train: list of training vectors.\n        k: how many neighbors to return.\n\n    Returns:\n        list[int]: indices into X_train, sorted by ascending distance.\n        Ties on distance are broken by smaller index.\n    \"\"\"\n    # TODO: compute l2_distance from query to every X_train[i], pair it\n    #       with its index, sort by (distance, index), and return the\n    #       first k indices.\n    raise NotImplementedError\n\n\ndef knn_classify(query, X_train, y_train, k):\n    \"\"\"Majority-vote KNN classification.\n\n    Args:\n        query: the query vector.\n        X_train: list of training vectors.\n        y_train: list of labels, same length as X_train.\n        k: number of neighbors to vote.\n\n    Returns:\n        the most frequent label among the k nearest neighbors. On a vote\n        tie, return the smallest tied label.\n    \"\"\"\n    # TODO: get the k nearest indices, count their labels, and return the\n    #       label with the highest count (smallest label wins a tie).\n    raise NotImplementedError\n\n\ndef knn_regress(query, X_train, y_train, k, weighted=False):\n    \"\"\"KNN regression: plain or distance-weighted average of targets.\n\n    Args:\n        query: the query vector.\n        X_train: list of training vectors.\n        y_train: list of numeric targets, same length as X_train.\n        k: number of neighbors to average.\n        weighted: if True, weight each neighbor by 1 / (distance + 1e-10);\n            if False, use a plain arithmetic mean.\n\n    Returns:\n        float: the predicted target value.\n    \"\"\"\n    # TODO: get the k nearest indices. If not weighted, return the plain\n    #       mean of their targets. If weighted, compute w_i = 1/(dist+1e-10)\n    #       and return sum(w_i * y_i) / sum(w_i).\n    raise NotImplementedError\n","tests":"import math\n\n# 1. l2_distance basics: 3-4-5 triangle, and zero distance to self.\nassert abs(l2_distance([0.0, 0.0], [3.0, 4.0]) - 5.0) < 1e-12\nassert abs(l2_distance([1.0, 2.0, 3.0], [1.0, 2.0, 3.0]) - 0.0) < 1e-12\n\n# 2. k_nearest returns the closest indices, sorted by distance.\nXq = [[0.0], [1.0], [2.0], [5.0]]\nassert k_nearest([0.1], Xq, 1) == [0]\nassert k_nearest([0.1], Xq, 2) == [0, 1]\n# A distance tie is broken by smaller index: 1.5 is equidistant to idx1 and idx2.\nassert k_nearest([1.5], Xq, 1) == [1]\n\n# 3. knn_classify: majority vote picks the dominant nearby class.\nX = [[0.0, 0.0], [0.1, 0.0], [0.0, 0.1], [5.0, 5.0], [5.1, 5.0]]\ny = ['a', 'a', 'a', 'b', 'b']\nassert knn_classify([0.05, 0.05], X, y, 3) == 'a'\nassert knn_classify([5.05, 5.0], X, y, 1) == 'b'\n# k=5 uses all points: 3 'a' vs 2 'b' -> 'a'.\nassert knn_classify([2.5, 2.5], X, y, 5) == 'a'\n\n# 4. knn_classify tie-break: equal votes resolve to the smaller label.\nXt = [[0.0], [1.0]]\nyt = [1, 0]\nassert knn_classify([0.5], Xt, yt, 2) == 0\n\n# 5. knn_regress unweighted: plain average of the k neighbor targets.\nXr = [[0.0], [1.0], [2.0], [3.0]]\nyr = [10.0, 20.0, 30.0, 40.0]\nassert abs(knn_regress([0.0], Xr, yr, 2) - 15.0) < 1e-9   # avg(10, 20)\nassert abs(knn_regress([1.5], Xr, yr, 2) - 25.0) < 1e-9   # avg(20, 30)\n\n# 6. knn_regress weighted: a near-exact match dominates the average.\nXw = [[0.0], [10.0]]\nyw = [1.0, 100.0]\npred = knn_regress([0.0], Xw, yw, 2, weighted=True)\nassert abs(pred - 1.0) < 0.5   # huge weight on the exact match -> close to 1.0\nplain = knn_regress([0.0], Xw, yw, 2, weighted=False)\nassert abs(plain - 50.5) < 1e-9\n","solution":"import math\n\n\ndef l2_distance(a, b):\n    \"\"\"Euclidean (L2) distance between two equal-length vectors.\"\"\"\n    return math.sqrt(sum((ai - bi) ** 2 for ai, bi in zip(a, b)))\n\n\ndef k_nearest(query, X_train, k):\n    \"\"\"Indices of the k training points closest to query (by L2).\"\"\"\n    dists = [(l2_distance(query, X_train[i]), i) for i in range(len(X_train))]\n    dists.sort(key=lambda pair: (pair[0], pair[1]))\n    return [idx for _, idx in dists[:k]]\n\n\ndef knn_classify(query, X_train, y_train, k):\n    \"\"\"Majority-vote KNN classification.\"\"\"\n    neighbor_idx = k_nearest(query, X_train, k)\n    votes = {}\n    for idx in neighbor_idx:\n        label = y_train[idx]\n        votes[label] = votes.get(label, 0) + 1\n    best_count = max(votes.values())\n    tied = [label for label, c in votes.items() if c == best_count]\n    return min(tied)\n\n\ndef knn_regress(query, X_train, y_train, k, weighted=False):\n    \"\"\"KNN regression: plain or distance-weighted average of targets.\"\"\"\n    neighbor_idx = k_nearest(query, X_train, k)\n    if not weighted:\n        return sum(y_train[i] for i in neighbor_idx) / len(neighbor_idx)\n    w_sum = 0.0\n    val_sum = 0.0\n    for i in neighbor_idx:\n        w = 1.0 / (l2_distance(query, X_train[i]) + 1e-10)\n        val_sum += w * y_train[i]\n        w_sum += w\n    return val_sum / w_sum\n","lessonId":"02-ml-fundamentals/06-knn-and-distances"}}